pyvarco/__init__.py
pyvarco/pyvarco.py
pyvarco-1.0.0.dist-info/LICENSE
pyvarco-1.0.0.dist-info/METADATA
pyvarco-1.0.0.dist-info/WHEEL
pyvarco-1.0.0.dist-info/top_level.txt
pyvarco-1.0.0.dist-info/RECORD
